README
setup.py
cvx/__init__.py
cvx/cvx.py
cvx.egg-info/PKG-INFO
cvx.egg-info/SOURCES.txt
cvx.egg-info/dependency_links.txt
cvx.egg-info/not-zip-safe
cvx.egg-info/requires.txt
cvx.egg-info/top_level.txt